pan_ztp_patcher/__init__.py
pan_ztp_patcher/app.py
pan_ztp_patcher/utils.py
pan_ztp_patcher/ztp_patcher.py
pan_ztp_patcher-0.2.10.dist-info/LICENSE
pan_ztp_patcher-0.2.10.dist-info/METADATA
pan_ztp_patcher-0.2.10.dist-info/WHEEL
pan_ztp_patcher-0.2.10.dist-info/entry_points.txt
pan_ztp_patcher-0.2.10.dist-info/RECORD
