Metadata-Version: 2.1
Name: pan-ztp-patcher
Version: 0.2.10
Summary: Update content version on PAN-OS firewalls
License: Apache2.0
Author: Calvin Remsburg
Author-email: cremsburg.dev@gmail.com
Requires-Python: >=3.8.1
Classifier: License :: Other/Proprietary License
Classifier: Programming Language :: Python :: 3
Classifier: Programming Language :: Python :: 3.9
Classifier: Programming Language :: Python :: 3.10
Classifier: Programming Language :: Python :: 3.11
Classifier: Programming Language :: Python :: 3.12
Requires-Dist: paramiko (>=3.4.0,<4.0.0)
Requires-Dist: python-dotenv (==0.21.1)
